capparser/__init__.py
capparser/capparser.py
capparser/element.py
capparser/enums.py
capparser-2.0.4.dist-info/LICENSE
capparser-2.0.4.dist-info/METADATA
capparser-2.0.4.dist-info/WHEEL
capparser-2.0.4.dist-info/top_level.txt
capparser-2.0.4.dist-info/RECORD
