Metadata-Version: 2.1
Name: capparser
Version: 2.0.4
Summary: Common Alerting Protocol (CAP) parser
Author: David Araújo
Author-email: david2araujo5@gmail.com
Classifier: Programming Language :: Python :: 3
Classifier: License :: OSI Approved :: MIT License
Classifier: Operating System :: OS Independent
Requires-Python: >=3.6
License-File: LICENSE
